pyproject.toml
setup.py
Laminos/__init__.py
Laminos/acm.py
Laminos/client.py
Laminos/socket.py
Laminos/sub_client.py
Laminos.egg-info/PKG-INFO
Laminos.egg-info/SOURCES.txt
Laminos.egg-info/dependency_links.txt
Laminos.egg-info/requires.txt
Laminos.egg-info/top_level.txt