Metadata-Version: 2.1
Name: Laminos
Version: 1.0.0
Summary: Laminos refixed amino
Home-page: UNKNOWN
Author: Legion, Fistack, Slavka jup, Mentoru
Author-email: laminos@inbox.ru
License: MIT
Download-URL: https://github.com/ImDefead/Laminos.py
Keywords: Re-bots,Amino-bots,Laminos-bots,capture,captureScapture-bot,capture-chat,capture-lib,cptr,cptr.co,api,python,python3,python3.x,Legions,Maybes,Dafters,Amino.py,Amino.py,Laminos,laminos.pyL-minos.py,lamino,lamino,laminos-bot,laminos-bots,laminos-bot,ndc,narvii.apps,aminoapps,lamino-py,lamino,lamino-bot,narvii,api,python,python3
Platform: UNKNOWN
